bookworm_genai/__init__.py
bookworm_genai/__main__.py
bookworm_genai/commands/__init__.py
bookworm_genai/commands/ask.py
bookworm_genai/commands/export.py
bookworm_genai/commands/sync.py
bookworm_genai/integrations.py
bookworm_genai/metadata.py
bookworm_genai/models.py
bookworm_genai/storage.py
bookworm_genai/utils.py
bookworm_genai-0.13.0.dist-info/LICENSE
bookworm_genai-0.13.0.dist-info/METADATA
bookworm_genai-0.13.0.dist-info/WHEEL
bookworm_genai-0.13.0.dist-info/entry_points.txt
bookworm_genai-0.13.0.dist-info/RECORD
