Metadata-Version: 2.1
Name: bookworm_genai
Version: 0.13.0
Summary: Bookworm - A LLM-powered bookmark search engine
Home-page: https://pypi.org/project/bookworm_genai/
License: MIT
Keywords: bookmarks,bookmark-manager,genai,chatbots
Author: kiran94
Requires-Python: >=3.9,<4.0
Classifier: Intended Audience :: Developers
Classifier: License :: OSI Approved :: MIT License
Classifier: Operating System :: OS Independent
Classifier: Programming Language :: Python :: 3
Classifier: Programming Language :: Python :: 3.9
Classifier: Programming Language :: Python :: 3.10
Classifier: Programming Language :: Python :: 3.11
Classifier: Programming Language :: Python :: 3.12
Classifier: Programming Language :: Python :: 3.13
Classifier: Topic :: Utilities
Requires-Dist: duckdb (>=1.0.0,<2.0.0)
Requires-Dist: jq (>=1.7.0,<2.0.0)
Requires-Dist: langchain (>=0.2.12,<0.3.0)
Requires-Dist: langchain-community (>=0.2.11,<0.3.0)
Requires-Dist: langchain-openai (>=0.1.20,<0.2.0)
Requires-Dist: pandas (>=2.2.2,<3.0.0)
Requires-Dist: platformdirs (>=4.2.2,<5.0.0)
Requires-Dist: rich (>=13.7.1,<14.0.0)
Requires-Dist: tiktoken (>=0.7.0,<0.8.0)
Project-URL: Documentation, https://github.com/kiran94/bookworm/blob/main/README.md
Project-URL: Repository, https://github.com/kiran94/bookworm
